hladl/__init__.py
hladl/download.py
hladl/get_seq.py
hladl/hladlfunctions.py
hladl/infer_allele.py
hladl/main.py
hladldata/__init__.py
hladl-0.2.0.dist-info/LICENSE
hladl-0.2.0.dist-info/METADATA
hladl-0.2.0.dist-info/WHEEL
hladl-0.2.0.dist-info/entry_points.txt
hladl-0.2.0.dist-info/RECORD
