Metadata-Version: 2.3
Name: hladl
Version: 0.2.0
Summary: Download and output HLA sequences from IPD-IMGT/HLA.
License: MIT
Author: Jamie Heather
Author-email: jheather@mgh.harvard.edu
Requires-Python: >=3.11
Classifier: License :: OSI Approved :: MIT License
Classifier: Programming Language :: Python :: 3
Classifier: Programming Language :: Python :: 3.11
Classifier: Programming Language :: Python :: 3.12
Classifier: Programming Language :: Python :: 3.13
Requires-Dist: acora (>=2.4)
Requires-Dist: requests (>=2.32.3,<3.0.0)
Requires-Dist: typer (>=0.15.2,<0.16.0)
